Orange3_spark-0.2.7-py3.5-nspkg.pth
Orange3_spark-0.2.7.dist-info/DESCRIPTION.rst
Orange3_spark-0.2.7.dist-info/METADATA
Orange3_spark-0.2.7.dist-info/RECORD
Orange3_spark-0.2.7.dist-info/WHEEL
Orange3_spark-0.2.7.dist-info/entry_points.txt
Orange3_spark-0.2.7.dist-info/metadata.json
Orange3_spark-0.2.7.dist-info/namespace_packages.txt
Orange3_spark-0.2.7.dist-info/top_level.txt
orangecontrib/spark/__init__.py
orangecontrib/spark/base/__init__.py
orangecontrib/spark/base/shared_spark_context.py
orangecontrib/spark/base/spark_ml_estimator.py
orangecontrib/spark/base/spark_ml_transformer.py
orangecontrib/spark/tutorials/__init__.py
orangecontrib/spark/tutorials/example_tutorial.ows
orangecontrib/spark/tutorials/spark_ml.ows
orangecontrib/spark/utils/__init__.py
orangecontrib/spark/utils/bdutils.py
orangecontrib/spark/utils/data_utils.py
orangecontrib/spark/utils/gui_utils.py
orangecontrib/spark/utils/ml_api_utils.py
orangecontrib/spark/utils/spark_api_utils.py
orangecontrib/spark/widgets/__init__.py
orangecontrib/spark/widgets/data/__init__.py
orangecontrib/spark/widgets/data/odbc_table.py
orangecontrib/spark/widgets/data/orange_to_pandas.py
orangecontrib/spark/widgets/data/pandas_to_orange.py
orangecontrib/spark/widgets/data/pyspark_script_console.py
orangecontrib/spark/widgets/data/spark_context.py
orangecontrib/spark/widgets/data/spark_df_cache.py
orangecontrib/spark/widgets/data/spark_fill.py
orangecontrib/spark/widgets/data/spark_from_orange.py
orangecontrib/spark/widgets/data/spark_from_pandas.py
orangecontrib/spark/widgets/data/spark_sample.py
orangecontrib/spark/widgets/data/spark_sql_dataframe.py
orangecontrib/spark/widgets/data/spark_table.py
orangecontrib/spark/widgets/data/spark_to_orange.py
orangecontrib/spark/widgets/data/spark_to_pandas.py
orangecontrib/spark/widgets/icons/Category-Classify.svg
orangecontrib/spark/widgets/icons/Category-Data.svg
orangecontrib/spark/widgets/icons/Category-Evaluate.svg
orangecontrib/spark/widgets/icons/Category-Regression.svg
orangecontrib/spark/widgets/icons/CodeCogsEqn.svg
orangecontrib/spark/widgets/icons/Concatenate.svg
orangecontrib/spark/widgets/icons/Continuize.svg
orangecontrib/spark/widgets/icons/DataInfo.svg
orangecontrib/spark/widgets/icons/DataSampler.svg
orangecontrib/spark/widgets/icons/Discretize.svg
