Metadata-Version: 2.0
Name: Orange3-spark
Version: 0.2.7
Summary: A series of Widgets for Orange3 to work with Spark ML
Home-page: https://github.com/jamartinh/Orange-Spark
Author: Jose Antonio Martin H.
Author-email: xjamartinh@gmail.com
License: Copyright (c) 2015 Jose Antonio Martin H.
Requires-Dist: Orange3
Requires-Dist: pandas
Requires-Dist: py4j
Requires-Dist: sqlparse
Provides-Extra: pyspark
